<annotation>
  <folder>images</folder>
  <filename>2171.jpg</filename>
  <path>C:/Users/andre/Downloads/archive (1)/Medical mask/Medical mask/Medical Mask/images/2171.jpg</path>
  <source>
    <database>Unknown</database>
  </source>
  <size>
    <width>713</width>
    <height>552</height>
    <depth>3</depth>
  </size>
  <segmented>0</segmented>
  <object>
    <name>face_with_mask</name>
    <pose>Unspecified</pose>
    <truncated>0</truncated>
    <difficult>0</difficult>
    <bndbox>
      <xmin>6</xmin>
      <ymin>176</ymin>
      <xmax>284</xmax>
      <ymax>552</ymax>
    </bndbox>
  </object>
  <object>
    <name>face_with_mask</name>
    <pose>Unspecified</pose>
    <truncated>0</truncated>
    <difficult>0</difficult>
    <bndbox>
      <xmin>443</xmin>
      <ymin>10</ymin>
      <xmax>711</xmax>
      <ymax>419</ymax>
    </bndbox>
  </object>
</annotation>
