<annotation>
  <folder>images</folder>
  <filename>2297.jpg</filename>
  <path>C:/Users/andre/Downloads/archive (1)/Medical mask/Medical mask/Medical Mask/images/2297.jpg</path>
  <source>
    <database>Unknown</database>
  </source>
  <size>
    <width>830</width>
    <height>368</height>
    <depth>3</depth>
  </size>
  <segmented>0</segmented>
  <object>
    <name>face_with_mask</name>
    <pose>Unspecified</pose>
    <truncated>0</truncated>
    <difficult>0</difficult>
    <bndbox>
      <xmin>383</xmin>
      <ymin>52</ymin>
      <xmax>582</xmax>
      <ymax>306</ymax>
    </bndbox>
  </object>
  <object>
    <name>face_no_mask</name>
    <pose>Unspecified</pose>
    <truncated>0</truncated>
    <difficult>0</difficult>
    <bndbox>
      <xmin>609</xmin>
      <ymin>0</ymin>
      <xmax>710</xmax>
      <ymax>48</ymax>
    </bndbox>
  </object>
</annotation>
