<annotation>
  <folder>images</folder>
  <filename>3409.jpg</filename>
  <path>C:/Users/andre/Downloads/archive (1)/Medical mask/Medical mask/Medical Mask/images/3409.jpg</path>
  <source>
    <database>Unknown</database>
  </source>
  <size>
    <width>523</width>
    <height>391</height>
    <depth>3</depth>
  </size>
  <segmented>0</segmented>
  <object>
    <name>face_with_mask</name>
    <pose>Unspecified</pose>
    <truncated>0</truncated>
    <difficult>0</difficult>
    <bndbox>
      <xmin>214</xmin>
      <ymin>14</ymin>
      <xmax>287</xmax>
      <ymax>112</ymax>
    </bndbox>
  </object>
  <object>
    <name>face_with_mask</name>
    <pose>Unspecified</pose>
    <truncated>0</truncated>
    <difficult>0</difficult>
    <bndbox>
      <xmin>346</xmin>
      <ymin>4</ymin>
      <xmax>425</xmax>
      <ymax>103</ymax>
    </bndbox>
  </object>
  <object>
    <name>face_with_mask</name>
    <pose>Unspecified</pose>
    <truncated>0</truncated>
    <difficult>0</difficult>
    <bndbox>
      <xmin>491</xmin>
      <ymin>51</ymin>
      <xmax>523</xmax>
      <ymax>120</ymax>
    </bndbox>
  </object>
</annotation>
