<annotation>
	<folder>images</folder>
	<filename>4089.png</filename>
	<path>C:\Users\andre\Downloads\archive (1)\Medical mask\Medical mask\Medical Mask\images\4089.png</path>
	<source>
		<database>Unknown</database>
	</source>
	<size>
		<width>889</width>
		<height>502</height>
		<depth>3</depth>
	</size>
	<segmented>0</segmented>
	<object>
		<name>face_with_mask</name>
		<pose>Unspecified</pose>
		<truncated>0</truncated>
		<difficult>0</difficult>
		<bndbox>
			<xmin>573</xmin>
			<ymin>130</ymin>
			<xmax>683</xmax>
			<ymax>285</ymax>
		</bndbox>
	</object>
	<object>
		<name>face_with_mask</name>
		<pose>Unspecified</pose>
		<truncated>0</truncated>
		<difficult>0</difficult>
		<bndbox>
			<xmin>449</xmin>
			<ymin>401</ymin>
			<xmax>618</xmax>
			<ymax>481</ymax>
		</bndbox>
	</object>
	<object>
		<name>face_with_mask</name>
		<pose>Unspecified</pose>
		<truncated>0</truncated>
		<difficult>0</difficult>
		<bndbox>
			<xmin>262</xmin>
			<ymin>27</ymin>
			<xmax>381</xmax>
			<ymax>169</ymax>
		</bndbox>
	</object>
</annotation>
