<annotation>
  <folder>images</folder>
  <filename>5704.jpg</filename>
  <path>C:/Users/andre/Downloads/archive (1)/Medical mask/Medical mask/Medical Mask/images/5704.jpg</path>
  <source>
    <database>Unknown</database>
  </source>
  <size>
    <width>1534</width>
    <height>2048</height>
    <depth>3</depth>
  </size>
  <segmented>0</segmented>
  <object>
    <name>face_with_mask</name>
    <pose>Unspecified</pose>
    <truncated>0</truncated>
    <difficult>0</difficult>
    <bndbox>
      <xmin>7</xmin>
      <ymin>661</ymin>
      <xmax>788</xmax>
      <ymax>1682</ymax>
    </bndbox>
  </object>
  <object>
    <name>face_with_mask</name>
    <pose>Unspecified</pose>
    <truncated>0</truncated>
    <difficult>0</difficult>
    <bndbox>
      <xmin>962</xmin>
      <ymin>904</ymin>
      <xmax>1424</xmax>
      <ymax>1556</ymax>
    </bndbox>
  </object>
</annotation>
